Metadata-Version: 1.0
Name: TRDstest
Version: 0.1.9
Summary: tensor ring decomposition toolbox
Home-page: UNKNOWN
Author: UNKNOWN
Author-email: UNKNOWN
License: BSD 3-Clause License
Keywords: pip,tensor,tensor ring decomposition,,
Platform: any
